CHANGES.txt
README.txt
ZopePublicLicense.txt
bootstrap.py
buildout.cfg
setup.py
src/zc/__init__.py
src/zc.displayname.egg-info/PKG-INFO
src/zc.displayname.egg-info/SOURCES.txt
src/zc.displayname.egg-info/dependency_links.txt
src/zc.displayname.egg-info/namespace_packages.txt
src/zc.displayname.egg-info/not-zip-safe
src/zc.displayname.egg-info/requires.txt
src/zc.displayname.egg-info/top_level.txt
src/zc/displayname/__init__.py
src/zc/displayname/adapters.py
src/zc/displayname/adapters.txt
src/zc/displayname/configure.zcml
src/zc/displayname/i18n.py
src/zc/displayname/interfaces.py
src/zc/displayname/tests.py