Metadata-Version: 1.0
Name: zc.displayname
Version: 1.1
Summary: A Zope 3 extension for pluggable display names.
